{"title":"Beenie Man Ft Akon - Unstoppable MP3 320 kbps, 2016","uid":15883807,"size":11072852,"categoryP":"audio","categoryS":"music","magnet":"?xt=urn:btih:0dd80afa22bf02025eea37af0e344bd5febd6fdb&amp;dn=Beenie+Man+Ft+Akon+-+Unstoppable+MP3+320+kbps%2C+2016&amp;tr=udp%3A%2F%2Ftracker.leechers-paradise.org%3A6969&amp;tr=udp%3A%2F%2Fzer0day.ch%3A1337&amp;tr=udp%3A%2F%2Fopen.demonii.com%3A1337&amp;tr=udp%3A%2F%2Ftracker.coppersurfer.tk%3A6969&amp;tr=udp%3A%2F%2Fexodus.desync.com%3A6969","seeders":9,"leechers":0,"uploader":"NikiPink","files":1,"time":1474633495,"description":"MP3 320 kbps\r\n\r\nGenre: Rap\r\n\r\nRelease Date: September 2016","torrent":{"xt":"urn:btih:0dd80afa22bf02025eea37af0e344bd5febd6fdb","amp;dn":"Beenie+Man+Ft+Akon+-+Unstoppable+MP3+320+kbps%2C+2016","amp;tr":["udp%3A%2F%2Ftracker.leechers-paradise.org%3A6969","udp%3A%2F%2Fzer0day.ch%3A1337","udp%3A%2F%2Fopen.demonii.com%3A1337","udp%3A%2F%2Ftracker.coppersurfer.tk%3A6969","udp%3A%2F%2Fexodus.desync.com%3A6969"],"infoHash":"0dd80afa22bf02025eea37af0e344bd5febd6fdb","infoHashBuffer":{"type":"Buffer","data":[13,216,10,250,34,191,2,2,94,234,55,175,14,52,75,213,254,189,111,219]},"announce":[],"urlList":[]}}