{"title":"[HorribleSubs] Sword Art Online II - Episode 04 [1080p]","uid":10641654,"size":568301507,"categoryP":"video","categoryS":"hd___tv_shows","magnet":"?xt=urn:btih:1687daa514889e3000259f0457430b0174abf6e0&amp;dn=%5BHorribleSubs%5D+Sword+Art+Online+II+-+Episode+04+%5B1080p%5D&amp;tr=udp%3A%2F%2Ftracker.openbittorrent.com%3A80&amp;tr=udp%3A%2F%2Fopen.demonii.com%3A1337&amp;tr=udp%3A%2F%2Ftracker.coppersurfer.tk%3A6969&amp;tr=udp%3A%2F%2Fexodus.desync.com%3A6969","seeders":9,"leechers":1,"uploader":"Ralphless","files":-1,"time":1406469257,"description":"Sword Art Online II - Episode 4 \n\nTitle: GGO (Gun Gale Online)\n\nQuality : 1080p\n\nAudio : Japanese\n\nSubtitles : English by Horrible Subs\n\nJapanese Air date: July 26, 2014\n\nFormat : MKV","torrent":{"xt":"urn:btih:1687daa514889e3000259f0457430b0174abf6e0","amp;dn":"%5BHorribleSubs%5D+Sword+Art+Online+II+-+Episode+04+%5B1080p%5D","amp;tr":["udp%3A%2F%2Ftracker.openbittorrent.com%3A80","udp%3A%2F%2Fopen.demonii.com%3A1337","udp%3A%2F%2Ftracker.coppersurfer.tk%3A6969","udp%3A%2F%2Fexodus.desync.com%3A6969"],"infoHash":"1687daa514889e3000259f0457430b0174abf6e0","infoHashBuffer":{"type":"Buffer","data":[22,135,218,165,20,136,158,48,0,37,159,4,87,67,11,1,116,171,246,224]},"announce":[],"urlList":[]}}