{"title":"Chris Brown-Don't Think They Know (feat. Aaliyah) [Single] [Muzi","uid":8594463,"size":9796281,"categoryP":"audio","categoryS":"music","magnet":"?xt=urn:btih:308e51ccbf4423ad7baba33c27ef1161e1482dfe&amp;dn=Chris+Brown-Don%27t+Think+They+Know+%28feat.+Aaliyah%29+%5BSingle%5D+%5BMuzi&amp;tr=udp%3A%2F%2Ftracker.openbittorrent.com%3A80&amp;tr=udp%3A%2F%2Fopen.demonii.com%3A1337&amp;tr=udp%3A%2F%2Ftracker.coppersurfer.tk%3A6969&amp;tr=udp%3A%2F%2Fexodus.desync.com%3A6969","seeders":9,"leechers":10,"uploader":"Deztructor","files":2,"time":1371724454,"description":"[b]===================================================================\nAlbum Info\n=====================================================================\n\n[img]http://img850.imageshack.us/img850/8398/b1yb.jpg[/img]\n\n\n\n- Format:- Mp3\n\n\n- Quality/bitrate:- 320 Kbps\n\n\n- Name of artist:- Chris Brown feat. Aaliyah\n\n\n- Name of Album:- Don't Think They Know (feat. Aaliyah) [Single]\n\n\n- Release Date:- 2013\n\n\n- Size:- 9.34 Mb\n\n\n- Genre:- R&amp;B/Soul\n\n\n[color=red]- Tracklist:-[/color]\n\n\n1) Don't Think They Know (feat. Aaliyah) [Single]\n\n\n\n\n[size=200][color=red]Plz seed to keep the torrent alive!!!\n\n\nThanx..:-)[/b][/color][/size]","torrent":{"xt":"urn:btih:308e51ccbf4423ad7baba33c27ef1161e1482dfe","amp;dn":"Chris+Brown-Don%27t+Think+They+Know+%28feat.+Aaliyah%29+%5BSingle%5D+%5BMuzi","amp;tr":["udp%3A%2F%2Ftracker.openbittorrent.com%3A80","udp%3A%2F%2Fopen.demonii.com%3A1337","udp%3A%2F%2Ftracker.coppersurfer.tk%3A6969","udp%3A%2F%2Fexodus.desync.com%3A6969"],"infoHash":"308e51ccbf4423ad7baba33c27ef1161e1482dfe","infoHashBuffer":{"type":"Buffer","data":[48,142,81,204,191,68,35,173,123,171,163,60,39,239,17,97,225,72,45,254]},"announce":[],"urlList":[]}}