{"title":"Dr. Strangelove (Or, How I Learned To Stop...) (1964)-JBW","uid":4115570,"size":1477796048,"categoryP":"video","categoryS":"movies","magnet":"?xt=urn:btih:332cbf525445db7866b6add02188f0de750f8174&amp;dn=Dr.+Strangelove+%28Or%2C+How+I+Learned+To+Stop...%29+%281964%29-JBW&amp;tr=udp%3A%2F%2Ftracker.openbittorrent.com%3A80&amp;tr=udp%3A%2F%2Fopen.demonii.com%3A1337&amp;tr=udp%3A%2F%2Ftracker.coppersurfer.tk%3A6969&amp;tr=udp%3A%2F%2Fexodus.desync.com%3A6969","seeders":9,"leechers":3,"uploader":"_Maelstrom_","files":-1,"time":1207289654,"description":"Dr. Strangelove (Or, How I Learned To Stop Worrying &amp; Love The Bomb) (1964)-JBW\n\n &lt;a href=&quot; http://imdb.com/title/tt0057012&quot; rel=&quot;nofollow&quot; target=&quot;_NEW&quot;&gt; http://imdb.com/title/tt0057012&lt;/a&gt;\n\n Source : Retail DVD\n Video Format : DivX 6.7.0.18\n Resolution : 720 x 448\n Framerate : 23.976\n Avg. Video Bitrate : 1687\n Aspect Ratio : Widescreen @ 1.60:1\n Audio Format : AC3\n Audio Bitrate : 448\n Audio Channels : 6\n Subtitles : English Only - SRT Format\n           : English, Francais, Chinese, Korean, Thai - SUB/IDX Format","torrent":{"xt":"urn:btih:332cbf525445db7866b6add02188f0de750f8174","amp;dn":"Dr.+Strangelove+%28Or%2C+How+I+Learned+To+Stop...%29+%281964%29-JBW","amp;tr":["udp%3A%2F%2Ftracker.openbittorrent.com%3A80","udp%3A%2F%2Fopen.demonii.com%3A1337","udp%3A%2F%2Ftracker.coppersurfer.tk%3A6969","udp%3A%2F%2Fexodus.desync.com%3A6969"],"infoHash":"332cbf525445db7866b6add02188f0de750f8174","infoHashBuffer":{"type":"Buffer","data":[51,44,191,82,84,69,219,120,102,182,173,208,33,136,240,222,117,15,129,116]},"announce":[],"urlList":[]}}