{"title":"Steal This Film (Part 1 AND 2)","uid":5299511,"size":734660608,"categoryP":"video","categoryS":"movies","magnet":"?xt=urn:btih:373b1794e9e73dbf206bce304a5900851193f285&amp;dn=Steal+This+Film+%28Part+1+AND+2%29&amp;tr=udp%3A%2F%2Ftracker.openbittorrent.com%3A80&amp;tr=udp%3A%2F%2Fopen.demonii.com%3A1337&amp;tr=udp%3A%2F%2Ftracker.coppersurfer.tk%3A6969&amp;tr=udp%3A%2F%2Fexodus.desync.com%3A6969","seeders":9,"leechers":0,"uploader":"euphorial","files":1,"time":1264174561,"description":"This is the highly sought &quot;Steal This Film&quot;, parts 1 *and* 2. It speaks of TPB raid in 2006, and freedom of sharing information.\n\nExcellent quality.\n\n\nEnjoy.\n//euphorial","torrent":{"xt":"urn:btih:373b1794e9e73dbf206bce304a5900851193f285","amp;dn":"Steal+This+Film+%28Part+1+AND+2%29","amp;tr":["udp%3A%2F%2Ftracker.openbittorrent.com%3A80","udp%3A%2F%2Fopen.demonii.com%3A1337","udp%3A%2F%2Ftracker.coppersurfer.tk%3A6969","udp%3A%2F%2Fexodus.desync.com%3A6969"],"infoHash":"373b1794e9e73dbf206bce304a5900851193f285","infoHashBuffer":{"type":"Buffer","data":[55,59,23,148,233,231,61,191,32,107,206,48,74,89,0,133,17,147,242,133]},"announce":[],"urlList":[]}}