{"title":"Despicable Me The Game (2010) [Wii][PAL][MULTi5]","uid":6064777,"size":1229447743,"categoryP":"games","categoryS":"wii","magnet":"?xt=urn:btih:4a6314463d0430f5e2974dab1619e99c8c22bede&amp;dn=Despicable+Me+The+Game+%282010%29+%5BWii%5D%5BPAL%5D%5BMULTi5%5D&amp;tr=udp%3A%2F%2Ftracker.openbittorrent.com%3A80&amp;tr=udp%3A%2F%2Fopen.demonii.com%3A1337&amp;tr=udp%3A%2F%2Ftracker.coppersurfer.tk%3A6969&amp;tr=udp%3A%2F%2Fexodus.desync.com%3A6969","seeders":9,"leechers":0,"uploader":"webchella","files":-1,"time":1293300386,"description":"Despicable Me The Game (2010) [Wii][PAL][MULTi5]\n &lt;a href=&quot;\nhttp://uk.wii.ign.com/objects/060/060142.html&quot; rel=&quot;nofollow&quot; target=&quot;_NEW&quot;&gt;\nhttp://uk.wii.ign.com/objects/060/060142.html&lt;/a&gt; &lt;a href=&quot;\nhttp://uk.wii.gamespy.com/wii/despicable-me/index.html&quot; rel=&quot;nofollow&quot; target=&quot;_NEW&quot;&gt;\nhttp://uk.wii.gamespy.com/wii/despicable-me/index.html&lt;/a&gt; &lt;a href=&quot;\nhttp://www.gamestore.cl/a-p/226-wii-despicable-me.html&quot; rel=&quot;nofollow&quot; target=&quot;_NEW&quot;&gt;\nhttp://www.gamestore.cl/a-p/226-wii-despicable-me.html&lt;/a&gt;\n\n===========\n::English::\n===========\nPlatform: Wii\nLanguage: English, Spanish, French, Italian, German\nFormat: ISO\nRegion: EUR\nGenre: Action\nPublisher: D3 Publisher\nDeveloper: Monkey Bar Games\nGambling facilities: 2 Versus\nRelease Date: TBA 2010\nAlso on: PSP, DS, PS2\n\nDescription:\n---------------\nExperience of the inventiveness of a genius contemptible as they Gru, the criminal mastermind of the CGI movie, worthless me. You plan robberies and attacks on arch-enemy plot Gru, Vector, as you work your way to greatness villain. I despised: The game offers a unique blend of action and puzzle solving that combines the fun of commanding an army of loyal followers-but-manic and use of an array of bizarre gadgets, weapons and vehicles to entertain players all ages.\n===========\n::Spanish::\n===========\nPlataforma: Wii\nIdioma: Ingles, EspaÃƒÂ±ol, Frances, Italiano, Aleman\nFormato: ISO\nRegion: EUR\nGÃƒÂ©nero: Accion\nEditor: D3 Publisher\nDesarrollador: Monkey Bar Juegos\nLocales de juego: 2 Versus\nFecha de PublicaciÃƒÂ³n: TBA 2010\nTambiÃƒÂ©n en: PSP, DS, PS2\n\nDescripcion:\n---------------\nExperiencia de la inventiva de ser un genio despreciable a medida que se Gru, el cerebro criminal de la pelÃƒÂ­cula CGI, despreciable mÃƒÂ­. Usted plan de robos y ataques parcela en archienemigo de Gru, Vector, como usted trabaja su manera a la grandeza villano. Me despreciable: El juego ofrece una mezcla ÃƒÂºnica de acciÃƒÂ³n y resoluciÃƒÂ³n de puzzles que combina la diversiÃƒÂ³n de mando de un ejÃƒÂ©rcito de leales secuaces-pero-manÃƒÂ­aco y el uso de un arsenal de artilugios extravagantes, armas y vehÃƒÂ­culos para entretener a los jugadores de todas las edades.\n","torrent":{"xt":"urn:btih:4a6314463d0430f5e2974dab1619e99c8c22bede","amp;dn":"Despicable+Me+The+Game+%282010%29+%5BWii%5D%5BPAL%5D%5BMULTi5%5D","amp;tr":["udp%3A%2F%2Ftracker.openbittorrent.com%3A80","udp%3A%2F%2Fopen.demonii.com%3A1337","udp%3A%2F%2Ftracker.coppersurfer.tk%3A6969","udp%3A%2F%2Fexodus.desync.com%3A6969"],"infoHash":"4a6314463d0430f5e2974dab1619e99c8c22bede","infoHashBuffer":{"type":"Buffer","data":[74,99,20,70,61,4,48,245,226,151,77,171,22,25,233,156,140,34,190,222]},"announce":[],"urlList":[]}}