{"title":"One Direction - One Way or Another (Teenage Kicks) [Live from th","uid":8176731,"size":8141850,"categoryP":"audio","categoryS":"music","magnet":"?xt=urn:btih:4f7bb46ca0a0b9f93d8c42c36e5538bf26a1cf08&amp;dn=One+Direction+-+One+Way+or+Another+%28Teenage+Kicks%29+%5BLive+from+th&amp;tr=udp%3A%2F%2Ftracker.openbittorrent.com%3A80&amp;tr=udp%3A%2F%2Fopen.demonii.com%3A1337&amp;tr=udp%3A%2F%2Ftracker.coppersurfer.tk%3A6969&amp;tr=udp%3A%2F%2Fexodus.desync.com%3A6969","seeders":8,"leechers":0,"uploader":"Oz","files":-1,"time":1361546235,"description":"General\n\nFormat : MPEG Audio\nFile size : 7.76 MiB\nDuration : 3mn 19s\nOverall bit rate mode : Constant\nOverall bit rate : 320 Kbps\nAlbum : One Way or Another (Teenage Kicks) [Live from the BRITs 2013] - Single\nAlbum/Performer : One Direction\nPart/Position : 1\nPart/Total : 1\nTrack name : One Way or Another (Teenage Kicks) [Live from the BRITs 2013]\nTrack name/Position : 1\nTrack name/Total : 1\nPerformer : One Direction\nEncoded by : Oz\nGenre : Pop\nRecorded date : 2013-02-20T08:00:00Z\nWriting library : LAME3.99.5\nCopyright : â„— 2013 BRIT Awards Limited\nCover : Yes\nCover type : Cover (front)\nCover MIME : image/jpg\n\nAudio\n\nFormat : MPEG Audio\nFormat version : Version 1\nFormat profile : Layer 3\nMode : Joint stereo\nDuration : 3mn 19s\nBit rate mode : Constant\nBit rate : 320 Kbps\nChannel(s) : 2 channels\nSampling rate : 44.1 KHz\nCompression mode : Lossy\nStream size : 7.61 MiB (98%)\nWriting library : LAME3.99.5\n\n\n***Don't Forget To Like My Page***\n\n   www face book com / HQMusiCOnlY","torrent":{"xt":"urn:btih:4f7bb46ca0a0b9f93d8c42c36e5538bf26a1cf08","amp;dn":"One+Direction+-+One+Way+or+Another+%28Teenage+Kicks%29+%5BLive+from+th","amp;tr":["udp%3A%2F%2Ftracker.openbittorrent.com%3A80","udp%3A%2F%2Fopen.demonii.com%3A1337","udp%3A%2F%2Ftracker.coppersurfer.tk%3A6969","udp%3A%2F%2Fexodus.desync.com%3A6969"],"infoHash":"4f7bb46ca0a0b9f93d8c42c36e5538bf26a1cf08","infoHashBuffer":{"type":"Buffer","data":[79,123,180,108,160,160,185,249,61,140,66,195,110,85,56,191,38,161,207,8]},"announce":[],"urlList":[]}}