{"title":"DriverGuide Toolkit 2.016.iso (With serial) - PRO-HACKER","uid":3527911,"size":5906432,"categoryP":"applications","categoryS":"windows","magnet":"?xt=urn:btih:52fee32009aa52621eb3da11fc9f2a34ce2338fc&amp;dn=DriverGuide+Toolkit+2.016.iso+%28With+serial%29+-+PRO-HACKER&amp;tr=udp%3A%2F%2Ftracker.openbittorrent.com%3A80&amp;tr=udp%3A%2F%2Fopen.demonii.com%3A1337&amp;tr=udp%3A%2F%2Ftracker.coppersurfer.tk%3A6969&amp;tr=udp%3A%2F%2Fexodus.desync.com%3A6969","seeders":9,"leechers":0,"uploader":"PRO-HACKER","files":1,"time":1158971174,"description":"PRO-HACKER!\n\n\nDriverGuide Toolkit identifies and lists drivers installed on your computer and, when connected to the Internet, allows you to search DriverGuide.com (and other sources) for driver updates and manufacturer sites. In addition, it allows you to backup your currently installed drivers for safe keeping. Backing up your Windows driver files means that they will be available to you the next time you need to reinstall the driver or the whole operating system. DriverGuide Toolkit places the driver files in one organized location of your choosing.\n\nDriverGuide Toolkit is especially helpful in situations where you have a computer in your possession and the internal hardware is unknown. DriverGuide Toolkit can identify the hardware on the system and the associated drivers, back them up to a specified location, and find the latest driver updates for them. DriverGude Toolkit is even network compatible - you can just as easily connect to a remote computer on your network, backup drivers, and find updates! \n &lt;a href=&quot;\nhttp://www.driverguidetoolkit.com/&quot; rel=&quot;nofollow&quot; target=&quot;_NEW&quot;&gt;\nhttp://www.driverguidetoolkit.com/&lt;/a&gt;\n\n\nSerial inside the ISO. .\nUse ISO Buster, WinRAR or PowerISO to extract the files.\n\n\n\nEnjoy! - PRO-HACKER","torrent":{"xt":"urn:btih:52fee32009aa52621eb3da11fc9f2a34ce2338fc","amp;dn":"DriverGuide+Toolkit+2.016.iso+%28With+serial%29+-+PRO-HACKER","amp;tr":["udp%3A%2F%2Ftracker.openbittorrent.com%3A80","udp%3A%2F%2Fopen.demonii.com%3A1337","udp%3A%2F%2Ftracker.coppersurfer.tk%3A6969","udp%3A%2F%2Fexodus.desync.com%3A6969"],"infoHash":"52fee32009aa52621eb3da11fc9f2a34ce2338fc","infoHashBuffer":{"type":"Buffer","data":[82,254,227,32,9,170,82,98,30,179,218,17,252,159,42,52,206,35,56,252]},"announce":[],"urlList":[]}}