{"title":"Breaking Bad S02E09 REPACK HDTV XviD-0TV [eztv]","uid":4885773,"size":366662388,"categoryP":"video","categoryS":"tv_shows","magnet":"?xt=urn:btih:5a58a1bf73ae5a105c708bea10db41d5389d225b&amp;dn=Breaking+Bad+S02E09+REPACK+HDTV+XviD-0TV+%5Beztv%5D&amp;tr=udp%3A%2F%2Ftracker.openbittorrent.com%3A80&amp;tr=udp%3A%2F%2Fopen.demonii.com%3A1337&amp;tr=udp%3A%2F%2Ftracker.coppersurfer.tk%3A6969&amp;tr=udp%3A%2F%2Fexodus.desync.com%3A6969","seeders":8,"leechers":1,"uploader":"eztv","files":1,"time":1241721149,"description":"#EZTV @ EFNet -&gt; http://eztv.it/\n\nWant to help us out? BitCoin: 1Fw4sRdZYFwULfeE7oQ91GLYKy8j5EcuFW","torrent":{"xt":"urn:btih:5a58a1bf73ae5a105c708bea10db41d5389d225b","amp;dn":"Breaking+Bad+S02E09+REPACK+HDTV+XviD-0TV+%5Beztv%5D","amp;tr":["udp%3A%2F%2Ftracker.openbittorrent.com%3A80","udp%3A%2F%2Fopen.demonii.com%3A1337","udp%3A%2F%2Ftracker.coppersurfer.tk%3A6969","udp%3A%2F%2Fexodus.desync.com%3A6969"],"infoHash":"5a58a1bf73ae5a105c708bea10db41d5389d225b","infoHashBuffer":{"type":"Buffer","data":[90,88,161,191,115,174,90,16,92,112,139,234,16,219,65,213,56,157,34,91]},"announce":[],"urlList":[]}}