{"title":"Bring Me The Horizon - Suicide Season (Deluxe) (iTunes Purchase)","uid":9427075,"size":221991202,"categoryP":"audio","categoryS":"other","magnet":"?xt=urn:btih:66345b6d852b7395f4f7d4834dc98c54bd58c4b1&amp;dn=Bring+Me+The+Horizon+-+Suicide+Season+%28Deluxe%29+%28iTunes+Purchase%29&amp;tr=udp%3A%2F%2Ftracker.openbittorrent.com%3A80&amp;tr=udp%3A%2F%2Fopen.demonii.com%3A1337&amp;tr=udp%3A%2F%2Ftracker.coppersurfer.tk%3A6969&amp;tr=udp%3A%2F%2Fexodus.desync.com%3A6969","seeders":8,"leechers":1,"uploader":"ImAussie","files":24,"time":1388725742,"description":"Artist: Bring Me The horizon\n\nAlbum: Suicide Season (Deluxe)\n\nLabel: (P) 2010 Visible Noise, Ltd., Under Exclusive License To Epitaph.\n\nKind: Purchased AAC audio files\n\nBit Rate: 256 Kbps\n\nSample Rate: 44.100kHz\n\nSEED AND ENJOY","torrent":{"xt":"urn:btih:66345b6d852b7395f4f7d4834dc98c54bd58c4b1","amp;dn":"Bring+Me+The+Horizon+-+Suicide+Season+%28Deluxe%29+%28iTunes+Purchase%29","amp;tr":["udp%3A%2F%2Ftracker.openbittorrent.com%3A80","udp%3A%2F%2Fopen.demonii.com%3A1337","udp%3A%2F%2Ftracker.coppersurfer.tk%3A6969","udp%3A%2F%2Fexodus.desync.com%3A6969"],"infoHash":"66345b6d852b7395f4f7d4834dc98c54bd58c4b1","infoHashBuffer":{"type":"Buffer","data":[102,52,91,109,133,43,115,149,244,247,212,131,77,201,140,84,189,88,196,177]},"announce":[],"urlList":[]}}