{"title":"Beetlejuice","uid":4456942,"size":827344287,"categoryP":"video","categoryS":"movies","magnet":"?xt=urn:btih:8222859d59a7f1744a2e738a50edb62295b700b6&amp;dn=Beetlejuice&amp;tr=udp%3A%2F%2Ftracker.openbittorrent.com%3A80&amp;tr=udp%3A%2F%2Fopen.demonii.com%3A1337&amp;tr=udp%3A%2F%2Ftracker.coppersurfer.tk%3A6969&amp;tr=udp%3A%2F%2Fexodus.desync.com%3A6969","seeders":9,"leechers":0,"uploader":"bigalow29","files":2,"time":1224526298,"description":"key words \nBeetle Juice \nBeetlejuice \nBeetleJuice1988 \n\nVideo: XviD \nbitrate 256 bit/s \naudio format mpg layer 3 \nMedia: Retail DVD \nFormat: stanterd 4:3 \nhight 720 \nwith 480 \nCropping/Clipping/Resizing: None \n\nBeetleJuice1988 \nAfter Barbara and Adam Maitland were killed in a car crash, they find themselves trapped \nas ghosts in their beautiful New England farmhouse. Their peace is disrupted when a yuppie \nfamily, the Deetzs, buy their house. The Maitlands are too nice and harmless as ghosts \nand all their efforts to scare the Deetzs away were unsuccessful. They eventually turn to \nanother ghost 'Beetlejuice' for help.. \n\nCast overview, first billed only: \n\nAlec Baldwin \n.... Adam \nGeena Davis .... Barbara \nAnnie McEnroe .... Jane Butterfield \nMaurice Page .... Ernie \nHugo Stanger .... Old Bill \nMichael Keaton \n.... Beetlejuice \nRachel Mittelman .... Little Jane \n\nFor more info visit : &lt;a href=&quot;\nhttp://www.imdb.com/title/tt0094721/&quot; rel=&quot;nofollow&quot; target=&quot;_NEW&quot;&gt;\nhttp://www.imdb.com/title/tt0094721/&lt;/a&gt; \n\nGenre: Comedy / Fantasy / Horror \nCountry: USA \nLanguage: English \nSource: DVDRip. \nTracked By Demonoid \n\n!!!!!~Enjoy and please remember to seed~!!!!!\n","torrent":{"xt":"urn:btih:8222859d59a7f1744a2e738a50edb62295b700b6","amp;dn":"Beetlejuice","amp;tr":["udp%3A%2F%2Ftracker.openbittorrent.com%3A80","udp%3A%2F%2Fopen.demonii.com%3A1337","udp%3A%2F%2Ftracker.coppersurfer.tk%3A6969","udp%3A%2F%2Fexodus.desync.com%3A6969"],"infoHash":"8222859d59a7f1744a2e738a50edb62295b700b6","infoHashBuffer":{"type":"Buffer","data":[130,34,133,157,89,167,241,116,74,46,115,138,80,237,182,34,149,183,0,182]},"announce":[],"urlList":[]}}