{"title":"Teenage Mutant Ninja Turtles Wii 2013","uid":9103350,"size":4699979776,"categoryP":"games","categoryS":"wii","magnet":"?xt=urn:btih:82643a083bb123d9b0b9ca1e4a420d154ba1f77b&amp;dn=Teenage+Mutant+Ninja+Turtles+Wii+2013&amp;tr=udp%3A%2F%2Ftracker.openbittorrent.com%3A80&amp;tr=udp%3A%2F%2Fopen.demonii.com%3A1337&amp;tr=udp%3A%2F%2Ftracker.coppersurfer.tk%3A6969&amp;tr=udp%3A%2F%2Fexodus.desync.com%3A6969","seeders":10,"leechers":3,"uploader":"dragomix","files":1,"time":1382808458,"description":"Teenage Mutant Ninja Turtles for Wii\n\nWorking\n\nTested on USB Loader GX","torrent":{"xt":"urn:btih:82643a083bb123d9b0b9ca1e4a420d154ba1f77b","amp;dn":"Teenage+Mutant+Ninja+Turtles+Wii+2013","amp;tr":["udp%3A%2F%2Ftracker.openbittorrent.com%3A80","udp%3A%2F%2Fopen.demonii.com%3A1337","udp%3A%2F%2Ftracker.coppersurfer.tk%3A6969","udp%3A%2F%2Fexodus.desync.com%3A6969"],"infoHash":"82643a083bb123d9b0b9ca1e4a420d154ba1f77b","infoHashBuffer":{"type":"Buffer","data":[130,100,58,8,59,177,35,217,176,185,202,30,74,66,13,21,75,161,247,123]},"announce":[],"urlList":[]}}