{"title":"The.Samaritan.Paradox-TiNYiSO","uid":10128688,"size":588719267,"categoryP":"games","categoryS":"pc","magnet":"?xt=urn:btih:85bd58c47aaa0ef71cba7e0b2638b46280d5f597&amp;dn=The.Samaritan.Paradox-TiNYiSO&amp;tr=udp%3A%2F%2Ftracker.openbittorrent.com%3A80&amp;tr=udp%3A%2F%2Fopen.demonii.com%3A1337&amp;tr=udp%3A%2F%2Ftracker.coppersurfer.tk%3A6969&amp;tr=udp%3A%2F%2Fexodus.desync.com%3A6969","seeders":8,"leechers":0,"uploader":"Mr.Stifmeister","files":3,"time":1399769094,"description":"\nProudly Presents\n\nThe Samaritan Paradox c) Screen 7\nDisk Amount/Format : 1 CD ISO\nMedia Protection Â  : Nothing\nA writer has died. His daughter seeks the help of you, Ord Salamon, to\nfind his secret last novel. During the search, questions will emerge\nDid her father really kill himself? What is the secret novel all about\nWhat is going on at the island of Fardo? Crack codes, decipher secrets\nfind a lost fortune in this exciting adventure for Windows PC\n\nOld-school style point &amp; click adventure\nFull English voice acting, 2+ lines\nHand-drawn art &amp; animation, 60+ rooms\nOriginal soundtrack by Lannie Neely , 45+ mins\nAdditional languages text only) included, EFIGS\n\nThe Samaritan Paradox is set in Sweden in the 80's. Ord Salomon has\nagreed to help Sara Bergwall find the book her father, Jonatan Bergwall\nwrote before he died. During the course of this treasure hunt, he learns\nthat Jonatan was investigating the weapons industry, and more\nspecifically some covert affairs with foreign dictatorships\n\nBut more questions arise. What is the book about, and why does Sara want\nOrd to find it for her? Did her Alzheimer's-stricken mother know the\nsecret before she grew too demented to share it? And how did Jonatan\nactually die\nBurn/mount, install, update, play\nGreetz: LARGEiSO and MEDIUMiSO\nSIZE DOES NOT MATTER","torrent":{"xt":"urn:btih:85bd58c47aaa0ef71cba7e0b2638b46280d5f597","amp;dn":"The.Samaritan.Paradox-TiNYiSO","amp;tr":["udp%3A%2F%2Ftracker.openbittorrent.com%3A80","udp%3A%2F%2Fopen.demonii.com%3A1337","udp%3A%2F%2Ftracker.coppersurfer.tk%3A6969","udp%3A%2F%2Fexodus.desync.com%3A6969"],"infoHash":"85bd58c47aaa0ef71cba7e0b2638b46280d5f597","infoHashBuffer":{"type":"Buffer","data":[133,189,88,196,122,170,14,247,28,186,126,11,38,56,180,98,128,213,245,151]},"announce":[],"urlList":[]}}