{"title":"Motown The Ultimate Collection (3 CDS)","uid":5993675,"size":217889266,"categoryP":"audio","categoryS":"music","magnet":"?xt=urn:btih:8a97abfc28cd09f1067bed4f4690a8df306cf148&amp;dn=Motown+The+Ultimate+Collection+%283+CDS%29&amp;tr=udp%3A%2F%2Ftracker.openbittorrent.com%3A80&amp;tr=udp%3A%2F%2Fopen.demonii.com%3A1337&amp;tr=udp%3A%2F%2Ftracker.coppersurfer.tk%3A6969&amp;tr=udp%3A%2F%2Fexodus.desync.com%3A6969","seeders":9,"leechers":0,"uploader":"TheShysta","files":67,"time":1290969995,"description":"                              (MP3) (CD RIP)\n\nDisc: 1  \n1.  Baby Love Single Version (Mono)  \n2.  Dancing In The Street Single Version  \n3.  The Tears Of A Clown Single Version (Mono)  \n4.  Stop! In The Name Of Love Single Version (Mono)  \n5.  Do You Love Me Single Version (Mono)  \n6.  The Tracks Of My Tears Album Version  \n7.  Ain't Too Proud To Beg Single Version (Mono)  \n8.  Going To A Go-Go Single Version (Mono)  \n9.  You Can't Hurry Love Single Version (Mono)  \n10. Get Ready Album Version (Stereo)  \n11. This Old Heart Of Mine (Is Weak For You) Single Version (Mono)  \n12. You Keep Me Hanging On Almighty Radio Edit  \n13. What Becomes Of The Brokenhearted Album Version  \n14. Reach Out, I'll Be There Edit  \n15. Heatwave Album Version (Stereo)  \n16. Bernadette Album Version (Stereo)  \n17. Jimmy Mack Album Version (Stereo)  \n18. Walk Away Renee Single Version (Mono)  \n19. Cloud Nine Single Version (Mono)  \n20. For Once In My Life Album Version  \n21. I Heard It Through The Grapevine Single Version (Mono)  \n22. Behind A Painted Smile Single Version  \n23. I Want You Back Original Version  \n24. Up The Ladder To The Roof Single Version  \n25. Too Busy Thinking About My Baby Single Version (Mono)  \n26. ABC (Album Version)  \n27. War (Album Version)\n  \nDisc: 2  \n1.  Signed, Sealed, Delivered (I'm Yours) Album Version  \n2.  River Deep, Mountain High Single Version  \n3.  It's A Shame Album Version  \n4.  I'll Be There Album Version  \n5.  Heaven Must Have Sent You Single Version (Mono)  \n6.  Stoned Love Album Version  \n7.  Just My Imagination (Running Away With Me) Single Version (Mono)  \n8.  What's Going On Single/Mono Mix  \n9.  Nathan Jones Single Version  \n10. Mercy Mercy Me (The Ecology) Album Version  \n11. Got To Be There Single Version  \n12. Papa Was A Rollin' Stone Edit  \n13. Touch Me In The Morning Single Version  \n14. Help Me Make It Through The Night Single Version  \n15. Let's Get It On Radio  \n16. Love Machine Album Version  \n17. Easy Album Version  \n18. You Are Everything Album Version  \n19. The Night Album Version  \n20. Theme From Mahogany  \n21. Brick House Album Version\n  \nDisc: 3  \n1.  Three Times A Lady Single Version  \n2.  Don't Leave Me This Way Single Version  \n3.  It's My House Album Version  \n4.  Still Single Version  \n5.  Being With You Single Version  \n6.  Upside Down Single Version  \n7.  Truly Album Version  \n8.  I'm Coming Out Single Version  \n9.  One Day In Your Life Album Version  \n10. All Night Long (All Night) Album Version  \n11. Superfreak Album Version  \n12. Penny Lover Album Version  \n13. Don't Look Any Further Single Version  \n14. Let's Get Serious Single Version  \n15. Say You, Say Me Album Version  \n16. Treat Her Like A Lady Single Version  \n17. Nightshift Album Version  \n18. Somebody's Watching Me Album Version  \n19. My Destiny Album Version  \n","torrent":{"xt":"urn:btih:8a97abfc28cd09f1067bed4f4690a8df306cf148","amp;dn":"Motown+The+Ultimate+Collection+%283+CDS%29","amp;tr":["udp%3A%2F%2Ftracker.openbittorrent.com%3A80","udp%3A%2F%2Fopen.demonii.com%3A1337","udp%3A%2F%2Ftracker.coppersurfer.tk%3A6969","udp%3A%2F%2Fexodus.desync.com%3A6969"],"infoHash":"8a97abfc28cd09f1067bed4f4690a8df306cf148","infoHashBuffer":{"type":"Buffer","data":[138,151,171,252,40,205,9,241,6,123,237,79,70,144,168,223,48,108,241,72]},"announce":[],"urlList":[]}}