{"title":"Danko Jones - Below The Belt (2010) [mp3@VBR]","uid":5579169,"size":105980667,"categoryP":"audio","categoryS":"music","magnet":"?xt=urn:btih:8eb377e51a145349ac1be753d21dc8c963c8108e&amp;dn=Danko+Jones+-+Below+The+Belt+%282010%29+%5Bmp3%40VBR%5D&amp;tr=udp%3A%2F%2Ftracker.openbittorrent.com%3A80&amp;tr=udp%3A%2F%2Fopen.demonii.com%3A1337&amp;tr=udp%3A%2F%2Ftracker.coppersurfer.tk%3A6969&amp;tr=udp%3A%2F%2Fexodus.desync.com%3A6969","seeders":9,"leechers":1,"uploader":"zibbik","files":-1,"time":1274477606,"description":"\nBand: Danko Jones\nAlbum: Below The Belt\nOrigin: Canada\nGenre: Hard Rock / Modern Rock\nTT: 41:40\n\nTracks:\n1. I Think BAd Thoughts\n2. Active Volcanoes\n3. Tonight Is Fine\n4. Magic Snake\n5. Had Enogh\n6. (I Can't Handle) Moderation\n7. Full Of Regret\n8. The Sore Loser\n9. Like Dynamite\n10. Apology Accepted\n11. I Wanna Break Up With You\n12 - Guest list blues (bonus track)\n13 - Rock 'n' roll proletariat (bonus track)\n &lt;a href=&quot;\nhttp://www.dankojones.com/&quot; rel=&quot;nofollow&quot; target=&quot;_NEW&quot;&gt;\nhttp://www.dankojones.com/&lt;/a&gt;\n\nMembers \nDanko Jones - Vocals/Guitar\nJohn Calabrese - Bass\nDan Cornelius - Drums ","torrent":{"xt":"urn:btih:8eb377e51a145349ac1be753d21dc8c963c8108e","amp;dn":"Danko+Jones+-+Below+The+Belt+%282010%29+%5Bmp3%40VBR%5D","amp;tr":["udp%3A%2F%2Ftracker.openbittorrent.com%3A80","udp%3A%2F%2Fopen.demonii.com%3A1337","udp%3A%2F%2Ftracker.coppersurfer.tk%3A6969","udp%3A%2F%2Fexodus.desync.com%3A6969"],"infoHash":"8eb377e51a145349ac1be753d21dc8c963c8108e","infoHashBuffer":{"type":"Buffer","data":[142,179,119,229,26,20,83,73,172,27,231,83,210,29,200,201,99,200,16,142]},"announce":[],"urlList":[]}}