{"title":"Schlussmacher.2013.BluRay.720p.DTS.x264-CHD [PublicHD]","uid":8615286,"size":4676448808,"categoryP":"video","categoryS":"hd___movies","magnet":"?xt=urn:btih:a36d717858f67428bbe3c24ae5aee4ed540a8535&amp;dn=Schlussmacher.2013.BluRay.720p.DTS.x264-CHD+%5BPublicHD%5D&amp;tr=udp%3A%2F%2Ftracker.openbittorrent.com%3A80&amp;tr=udp%3A%2F%2Fopen.demonii.com%3A1337&amp;tr=udp%3A%2F%2Ftracker.coppersurfer.tk%3A6969&amp;tr=udp%3A%2F%2Fexodus.desync.com%3A6969","seeders":8,"leechers":1,"uploader":"aoloffline","files":3,"time":1372237377,"description":"                PublicHD - High-Definition Bittorrent Community\n      \n                           &lt;a href=&quot; https://publichd.se/&quot; rel=&quot;nofollow&quot; target=&quot;_NEW&quot;&gt; https://publichd.se/&lt;/a&gt;\n    \n              ----------------------------------------------------\n\nSchlussmacher.2013.BluRay.720p.DTS.x264-CHD [PublicHD]\n &lt;a href=&quot;\nhttp://www.imdb.com/title/tt1978524&quot; rel=&quot;nofollow&quot; target=&quot;_NEW&quot;&gt;\nhttp://www.imdb.com/title/tt1978524&lt;/a&gt;\n\nRELEASE DATE....: 06/26/2013\nTHEATRE DATE....: 2013\n\nGENRE...........: Comedy\nSOURCE..........: Schlussmacher 2013 BluRay 1080p AVC DTS-HD MA5.1-CHDBits\nViDEO BiTRATE...: x264 @ 4133 Kbps\nFRAME RATE......: 23.976 fps\nAUDiO 1.........: GER DTS-CORE 5.1CH @ 1536 Kbps\nRUNTiME 1.......: 01:50:31 (h:m:s)\nASPECT RATiO....: 2.353: 1\nRESOLUTiON......: 1280 X 544\nSUBTiTLES.......: N/A\nFilE SiZE.......: 4.35G\nEncoder.........: @CHD\n\n\nSCREENS\n &lt;a href=&quot;\nhttp://i.imgbox.com/adw7nC8A.png&quot; rel=&quot;nofollow&quot; target=&quot;_NEW&quot;&gt;\nhttp://i.imgbox.com/adw7nC8A.png&lt;/a&gt;\n &lt;a href=&quot;\nhttp://i.imgbox.com/aclnwYhO.png&quot; rel=&quot;nofollow&quot; target=&quot;_NEW&quot;&gt;\nhttp://i.imgbox.com/aclnwYhO.png&lt;/a&gt;\n &lt;a href=&quot;\nhttp://i.imgbox.com/actmAg3l.png&quot; rel=&quot;nofollow&quot; target=&quot;_NEW&quot;&gt;\nhttp://i.imgbox.com/actmAg3l.png&lt;/a&gt;\n &lt;a href=&quot;\nhttp://i.imgbox.com/adv1q3jr.png&quot; rel=&quot;nofollow&quot; target=&quot;_NEW&quot;&gt;\nhttp://i.imgbox.com/adv1q3jr.png&lt;/a&gt;\n &lt;a href=&quot;\nhttp://i.imgbox.com/adtPkYyc.png&quot; rel=&quot;nofollow&quot; target=&quot;_NEW&quot;&gt;\nhttp://i.imgbox.com/adtPkYyc.png&lt;/a&gt;\n &lt;a href=&quot;\nhttp://i.imgbox.com/adrXzHjT.png&quot; rel=&quot;nofollow&quot; target=&quot;_NEW&quot;&gt;\nhttp://i.imgbox.com/adrXzHjT.png&lt;/a&gt;\n","torrent":{"xt":"urn:btih:a36d717858f67428bbe3c24ae5aee4ed540a8535","amp;dn":"Schlussmacher.2013.BluRay.720p.DTS.x264-CHD+%5BPublicHD%5D","amp;tr":["udp%3A%2F%2Ftracker.openbittorrent.com%3A80","udp%3A%2F%2Fopen.demonii.com%3A1337","udp%3A%2F%2Ftracker.coppersurfer.tk%3A6969","udp%3A%2F%2Fexodus.desync.com%3A6969"],"infoHash":"a36d717858f67428bbe3c24ae5aee4ed540a8535","infoHashBuffer":{"type":"Buffer","data":[163,109,113,120,88,246,116,40,187,227,194,74,229,174,228,237,84,10,133,53]},"announce":[],"urlList":[]}}