{"title":"Jenni Rivera - Discografia - CD's MP3","uid":4454550,"size":300606743,"categoryP":"audio","categoryS":"music","magnet":"?xt=urn:btih:a847d293c19d3ecd908c93f00385e6e9130f9a2f&amp;dn=Jenni+Rivera+-+Discografia+-+CD%5C%27s+MP3&amp;tr=udp%3A%2F%2Ftracker.openbittorrent.com%3A80&amp;tr=udp%3A%2F%2Fopen.demonii.com%3A1337&amp;tr=udp%3A%2F%2Ftracker.coppersurfer.tk%3A6969&amp;tr=udp%3A%2F%2Fexodus.desync.com%3A6969","seeders":8,"leechers":0,"uploader":"TheLabMan","files":66,"time":1224376382,"description":"                         Jenni Rivera\n\n   \nJenni Rivera - Jenni\n       01-Chuper Amigos.mp3\n       02-Culpable O Inocente.mp3\n       03-Envuelvete.mp3\n       04-Tu Camisa Puesta.mp3\n       05-Ni Me Viene Ni Me Va.mp3\n       06-Con El.mp3\n       07-Cuando Me Acuerdo De Ti.mp3\n       08-Fraude.mp3\n       09-Trono Caido.mp3\n       10-Vale La Pena.mp3\n       11-La Cama.mp3\n       12-Mudanzas.mp3\n       13-Culpable O Inocente (Version Pop).mp3\n       14-La Primera Piedra.mp3\n       jenni.jpg\n       \nJenni Rivera - La Diva En Vivo\n       01 - Jenni Rivera - La Diva En Vivo - 2007 - Sufriendo A Solas.mp3\n       02 - Jenni Rivera - La Diva En Vivo - 2007 - Por Un Amor - Cucurrucucu Paloma.mp3\n       03 - Jenni Rivera - La Diva En Vivo - 2007 - La Diferencia.mp3\n       04 - Jenni Rivera - La Diva En Vivo - 2007 - Inocente Pobre Amiga.mp3\n       05 - Jenni Rivera - La Diva En Vivo - 2007 - Paloma Negra.mp3\n       06 - Jenni Rivera - La Diva En Vivo - 2007 - Libro Abierto.mp3\n       07 - Jenni Rivera - La Diva En Vivo - 2007 - Me Siento Libre.mp3\n       08 - Jenni Rivera - La Diva En Vivo - 2007 - Brincos Dieras.mp3\n       09 - Jenni Rivera - La Diva En Vivo - 2007 - Que Me Vas A Dar.mp3\n       10 - Jenni Rivera - La Diva En Vivo - 2007 - De Contrabando.mp3\n       11 - Jenni Rivera - La Diva En Vivo - 2007 - La Mentada Contestada.mp3\n       12 - Jenni Rivera - La Diva En Vivo - 2007 - Navidad Sin Ti.mp3\n       Jenni Rivera - La Diva En Vivo - 2007.jpg\n       Jenni.jpg\n       \nJenni Rivera - Mi Vida Loca\n       01-jenni_rivera-mi_vida_loca.mp3\n       02-jenni_rivera-la_sopa_del_bebe.mp3\n       03-jenni_rivera-besos_y_copas.mp3\n       04-jenni_rivera-mil_heridas.mp3\n       05-jenni_rivera-la_tequilera.mp3\n       06-jenni_rivera-ese_hombre.mp3\n       07-jenni_rivera-a_escondidas.mp3\n       08-jenni_rivera-el_vato_gacho.mp3\n       09-jenni_rivera-me_siento_libre.mp3\n       10-jenni_rivera-que_me_vas_a_dar.mp3\n       11-jenni_rivera-parrandera_rebelde_y_atrevida.mp3\n       12-jenni_rivera-de_contrabando.mp3\n       13-jenni_rivera-bricos_dieras.mp3\n       14-jenni_rivera-la_mentada_contestada.mp3\n       15-jenni_rivera-no_vas_a_creer.mp3\n       16-jenni_rivera-imbecil.mp3\n       17-jenni_rivera-no_me_pregunten_por_el.mp3\n       18-jenni_rivera-que_se_te_olvido.mp3\n       19-jenni_rivera-jefa_de_jefas.mp3\n       20-jenni_rivera-las_malandrinas.mp3\n       21-jenni_rivera-se_las_voy_a_dar_a_otro.mp3\n       22-jenni_rivera-cuando_muere_una_dama.mp3\n       Jenni.jpg\n       jr.jpg\n       \nJenni Rivera - Si Quieres Verme Llorar\n       01 Brincos Dieras.mp3\n       02 Perdonar Es Olvidar.mp3\n       03 Llanto Rojo.mp3\n       04 Lagrimas, Sudor y Sangre.mp3\n       05 La Puerta de Alcala.mp3\n       06 Si Quieres Verme Llorar.mp3\n       07 Vivir Sin Tu Carino (Without You).mp3\n       08 Nosotros.mp3\n       09 Como Vivir Sin Verte (How Do I Live).mp3\n       10 Tonto.mp3\n       11 Yo Te Agradezco.mp3\n       jenni.jpg\n       Portada.jpg\n        \n","torrent":{"xt":"urn:btih:a847d293c19d3ecd908c93f00385e6e9130f9a2f","amp;dn":"Jenni+Rivera+-+Discografia+-+CD%5C%27s+MP3","amp;tr":["udp%3A%2F%2Ftracker.openbittorrent.com%3A80","udp%3A%2F%2Fopen.demonii.com%3A1337","udp%3A%2F%2Ftracker.coppersurfer.tk%3A6969","udp%3A%2F%2Fexodus.desync.com%3A6969"],"infoHash":"a847d293c19d3ecd908c93f00385e6e9130f9a2f","infoHashBuffer":{"type":"Buffer","data":[168,71,210,147,193,157,62,205,144,140,147,240,3,133,230,233,19,15,154,47]},"announce":[],"urlList":[]}}