{"title":"[ExxxtraSmall] Holly Hendrix - Stranded Teen Gets Picked Up and ","uid":12249558,"size":546843281,"categoryP":"porn","categoryS":"other","magnet":"?xt=urn:btih:b89a2641ae541ea10f01f5a6ebc29c987c92d1fd&amp;dn=%5BExxxtraSmall%5D+Holly+Hendrix+-+Stranded+Teen+Gets+Picked+Up+and+&amp;tr=udp%3A%2F%2Ftracker.openbittorrent.com%3A80&amp;tr=udp%3A%2F%2Fopen.demonii.com%3A1337&amp;tr=udp%3A%2F%2Ftracker.coppersurfer.tk%3A6969&amp;tr=udp%3A%2F%2Fexodus.desync.com%3A6969","seeders":9,"leechers":0,"uploader":"juggs99","files":2,"time":1439989596,"description":"Genre: Legal Teen, Cum in Mouth, BlowJobs, Gonzo, Hardcore, All Sex\n\nDuration: 00:46:22\n &lt;a href=&quot;\nhttp://HotImage.uk/img-55d462cc55daf.html&quot; rel=&quot;nofollow&quot; target=&quot;_NEW&quot;&gt;\nhttp://HotImage.uk/img-55d462cc55daf.html&lt;/a&gt;\n &lt;a href=&quot;\nhttp://HotImage.uk/img-55d462ccb8e1c.html&quot; rel=&quot;nofollow&quot; target=&quot;_NEW&quot;&gt;\nhttp://HotImage.uk/img-55d462ccb8e1c.html&lt;/a&gt;\n &lt;a href=&quot;\nhttp://HotImage.uk/img-55d462ccc067d.html&quot; rel=&quot;nofollow&quot; target=&quot;_NEW&quot;&gt;\nhttp://HotImage.uk/img-55d462ccc067d.html&lt;/a&gt;\n &lt;a href=&quot;\nhttp://HotImage.uk/img-55d462ccc7b37.html&quot; rel=&quot;nofollow&quot; target=&quot;_NEW&quot;&gt;\nhttp://HotImage.uk/img-55d462ccc7b37.html&lt;/a&gt;","torrent":{"xt":"urn:btih:b89a2641ae541ea10f01f5a6ebc29c987c92d1fd","amp;dn":"%5BExxxtraSmall%5D+Holly+Hendrix+-+Stranded+Teen+Gets+Picked+Up+and+","amp;tr":["udp%3A%2F%2Ftracker.openbittorrent.com%3A80","udp%3A%2F%2Fopen.demonii.com%3A1337","udp%3A%2F%2Ftracker.coppersurfer.tk%3A6969","udp%3A%2F%2Fexodus.desync.com%3A6969"],"infoHash":"b89a2641ae541ea10f01f5a6ebc29c987c92d1fd","infoHashBuffer":{"type":"Buffer","data":[184,154,38,65,174,84,30,161,15,1,245,166,235,194,156,152,124,146,209,253]},"announce":[],"urlList":[]}}