{"title":"Courtney love-Americas Sweetheart 2004","uid":3320766,"size":83096690,"categoryP":"audio","categoryS":"music","magnet":"?xt=urn:btih:cdb97b7c6c4e40c09869952dda7e4f5bf45437d4&amp;dn=Courtney+love-Americas+Sweetheart+2004&amp;tr=udp%3A%2F%2Ftracker.openbittorrent.com%3A80&amp;tr=udp%3A%2F%2Fopen.demonii.com%3A1337&amp;tr=udp%3A%2F%2Ftracker.coppersurfer.tk%3A6969&amp;tr=udp%3A%2F%2Fexodus.desync.com%3A6969","seeders":9,"leechers":0,"uploader":"thomlea","files":13,"time":1114300014,"description":"This is a request...\n\n12 tracks in playlist, average track length: 3:55\nPlaylist length: 47 minutes 1 second\n\n    Playlist files:\n\n          1. Courtney love - mono (3:39)\n          2. Courtney love - but julian im a little older t (2:48)\n          3. Courtney love - hold on tome (3:45)\n          4. Courtney love - sunset strip (5:52)\n          5. Courtney love - all the drugs (4:31)\n          6. Courtney love - alomost golden (3:25)\n          7. Courtney love - ill do anything (3:01)\n          8. Courtney love - uncool (4:37)\n          9. Courtney love - plague (4:16)\n          10. Courtney love - hello (3:10)\n          11. Courtney love - zeppelin song (2:48)\n          12. Courtney love - never gonna be the same (5:09)","torrent":{"xt":"urn:btih:cdb97b7c6c4e40c09869952dda7e4f5bf45437d4","amp;dn":"Courtney+love-Americas+Sweetheart+2004","amp;tr":["udp%3A%2F%2Ftracker.openbittorrent.com%3A80","udp%3A%2F%2Fopen.demonii.com%3A1337","udp%3A%2F%2Ftracker.coppersurfer.tk%3A6969","udp%3A%2F%2Fexodus.desync.com%3A6969"],"infoHash":"cdb97b7c6c4e40c09869952dda7e4f5bf45437d4","infoHashBuffer":{"type":"Buffer","data":[205,185,123,124,108,78,64,192,152,105,149,45,218,126,79,91,244,84,55,212]},"announce":[],"urlList":[]}}