{"title":"Ben.Hur.2010.DVDRip.XviD-ViP3R","uid":6382750,"size":1478932839,"categoryP":"video","categoryS":"movies","magnet":"?xt=urn:btih:d0214a6b090f5f71a2a79096ef6e0cef322b9124&amp;dn=Ben.Hur.2010.DVDRip.XviD-ViP3R&amp;tr=udp%3A%2F%2Ftracker.openbittorrent.com%3A80&amp;tr=udp%3A%2F%2Fopen.demonii.com%3A1337&amp;tr=udp%3A%2F%2Ftracker.coppersurfer.tk%3A6969&amp;tr=udp%3A%2F%2Fexodus.desync.com%3A6969","seeders":9,"leechers":2,"uploader":"etlover","files":5,"time":1305088723,"description":"Ben.Hur.2010.DVDRip.XviD-ViP3R\n\nTiTLE.........[ Ben Hur\nAUDiO.........[ 48000Hz  128 kb/s\nLANGUAGE......[ English\nViDEO.........[ 931 kbps XviD 25.000 FPS\nRESOLUTiON....[ 640 x 368\nASPECT RATiO..[ 1.739\nSUBS..........[ English\nFiLES.........[ 1\nSiZE..........[ 1.4GB\nRUNTIME.......[ 3:04:33\nGENRE.........[ Action | Drama      \nRARS..........[ Never\n\nIMDb URL: http://www.imdb.com/title/tt1421499/\nIMDB Rating: 5.9/10 (349 votes)\nCAST:\nJoseph Morgan, Stephen Campbell Moore, Emily VanCamp\n\nPLOT:\nAbout the struggle between the Roman Empire and its rebellious \nconquest Judaea, and two best friends caught in a terrible moment \nin history\n\nBeware Of Fakers, Only Download From Trusted Sources\n\n\nSCREENS\n &lt;a href=&quot;\nhttp://imageshack.us/m/718/7494/vlcsnap2011051100h43m58.png&quot; rel=&quot;nofollow&quot; target=&quot;_NEW&quot;&gt;\nhttp://imageshack.us/m/718/7494/vlcsnap2011051100h43m58.png&lt;/a&gt;\n &lt;a href=&quot;\nhttp://imageshack.us/m/851/5217/vlcsnap2011051100h44m25.png&quot; rel=&quot;nofollow&quot; target=&quot;_NEW&quot;&gt;\nhttp://imageshack.us/m/851/5217/vlcsnap2011051100h44m25.png&lt;/a&gt;\n &lt;a href=&quot;\nhttp://imageshack.us/m/848/7537/vlcsnap2011051100h45m10.png&quot; rel=&quot;nofollow&quot; target=&quot;_NEW&quot;&gt;\nhttp://imageshack.us/m/848/7537/vlcsnap2011051100h45m10.png&lt;/a&gt;","torrent":{"xt":"urn:btih:d0214a6b090f5f71a2a79096ef6e0cef322b9124","amp;dn":"Ben.Hur.2010.DVDRip.XviD-ViP3R","amp;tr":["udp%3A%2F%2Ftracker.openbittorrent.com%3A80","udp%3A%2F%2Fopen.demonii.com%3A1337","udp%3A%2F%2Ftracker.coppersurfer.tk%3A6969","udp%3A%2F%2Fexodus.desync.com%3A6969"],"infoHash":"d0214a6b090f5f71a2a79096ef6e0cef322b9124","infoHashBuffer":{"type":"Buffer","data":[208,33,74,107,9,15,95,113,162,167,144,150,239,110,12,239,50,43,145,36]},"announce":[],"urlList":[]}}