{"title":"BLACKED - Karina White (Girlfriend Cheats With BBC on Vacation)","uid":15792616,"size":325972858,"categoryP":"porn","categoryS":"movie_clips","magnet":"?xt=urn:btih:d0d58ec168711ae1e68964c5d95103fd1cb38bb6&amp;dn=BLACKED+-+Karina+White+%28Girlfriend+Cheats+With+BBC+on+Vacation%29+&amp;tr=udp%3A%2F%2Ftracker.leechers-paradise.org%3A6969&amp;tr=udp%3A%2F%2Fzer0day.ch%3A1337&amp;tr=udp%3A%2F%2Fopen.demonii.com%3A1337&amp;tr=udp%3A%2F%2Ftracker.coppersurfer.tk%3A6969&amp;tr=udp%3A%2F%2Fexodus.desync.com%3A6969","seeders":9,"leechers":2,"uploader":"SudoSu","files":1,"time":1473400507,"description":"http://youpornbook.com\r\n\r\n――――――――――――――――\r\n Screen source:\r\n―――――――――――――――― \nhttp://imgreborn.com/?v=633211 \nhttp://imgreborn.com/?v=700393 \nhttp://imgreborn.com/?v=787866\r\n\r\nBeautiful Karina. She has been left all alone for the first day of her vacation because her boyfriend has been held up at work. She doesn't let her revealing new swimsuit go to waste though,and goes down to the pool for a few drinks in the hot sunshine, showing off her stunning curves. While she enjoys her gorgeous surroundings, she is joined by Jason, a hot black guy who is at the hotel too. She is feeling a little frustrated, and he is soon alleviating this by caressing her gently and getting her pulse racing like she could never have imagined. She knows it’s wrong, but before long, the sexual tension is clear to see and they take it back to Karina’s room, where her thoughts of her absent boyfriend are sure to be a distant memory.\r\n\r\nMore exclusive porn at:  https://thepiratebay.org/user/SudoSu/","torrent":{"xt":"urn:btih:d0d58ec168711ae1e68964c5d95103fd1cb38bb6","amp;dn":"BLACKED+-+Karina+White+%28Girlfriend+Cheats+With+BBC+on+Vacation%29+","amp;tr":["udp%3A%2F%2Ftracker.leechers-paradise.org%3A6969","udp%3A%2F%2Fzer0day.ch%3A1337","udp%3A%2F%2Fopen.demonii.com%3A1337","udp%3A%2F%2Ftracker.coppersurfer.tk%3A6969","udp%3A%2F%2Fexodus.desync.com%3A6969"],"infoHash":"d0d58ec168711ae1e68964c5d95103fd1cb38bb6","infoHashBuffer":{"type":"Buffer","data":[208,213,142,193,104,113,26,225,230,137,100,197,217,81,3,253,28,179,139,182]},"announce":[],"urlList":[]}}