{"title":"[MyBabysittersClub] Keisha Grey - How Bad Do You Want This Job (","uid":14715143,"size":570421808,"categoryP":"porn","categoryS":"movie_clips","magnet":"?xt=urn:btih:d1f04cf7c2d862d66387a01e98b260fcc71a04ef&amp;dn=%5BMyBabysittersClub%5D+Keisha+Grey+-+How+Bad+Do+You+Want+This+Job+%28&amp;tr=udp%3A%2F%2Ftracker.leechers-paradise.org%3A6969&amp;tr=udp%3A%2F%2Fzer0day.ch%3A1337&amp;tr=udp%3A%2F%2Fopen.demonii.com%3A1337&amp;tr=udp%3A%2F%2Ftracker.coppersurfer.tk%3A6969&amp;tr=udp%3A%2F%2Fexodus.desync.com%3A6969","seeders":9,"leechers":3,"uploader":"KayWily","files":1,"time":1464457471,"description":"[MyBabysittersClub] Keisha Grey - How Bad Do You Want This Job (28.05.2016) \r\n\r\n \nhttp://porn-harbor.com/image/NDX","torrent":{"xt":"urn:btih:d1f04cf7c2d862d66387a01e98b260fcc71a04ef","amp;dn":"%5BMyBabysittersClub%5D+Keisha+Grey+-+How+Bad+Do+You+Want+This+Job+%28","amp;tr":["udp%3A%2F%2Ftracker.leechers-paradise.org%3A6969","udp%3A%2F%2Fzer0day.ch%3A1337","udp%3A%2F%2Fopen.demonii.com%3A1337","udp%3A%2F%2Ftracker.coppersurfer.tk%3A6969","udp%3A%2F%2Fexodus.desync.com%3A6969"],"infoHash":"d1f04cf7c2d862d66387a01e98b260fcc71a04ef","infoHashBuffer":{"type":"Buffer","data":[209,240,76,247,194,216,98,214,99,135,160,30,152,178,96,252,199,26,4,239]},"announce":[],"urlList":[]}}