{"title":"Mutantes","uid":3978137,"size":493470172,"categoryP":"audio","categoryS":"music","magnet":"?xt=urn:btih:d4efcf83d0ee44b7da9543abd7b90d4333281419&amp;dn=Mutantes&amp;tr=udp%3A%2F%2Ftracker.openbittorrent.com%3A80&amp;tr=udp%3A%2F%2Fopen.demonii.com%3A1337&amp;tr=udp%3A%2F%2Ftracker.coppersurfer.tk%3A6969&amp;tr=udp%3A%2F%2Fexodus.desync.com%3A6969","seeders":9,"leechers":3,"uploader":"sac_cb","files":137,"time":1200402171,"description":"Os Mutantes- Discografia Completa, MP3  min 192 kbps","torrent":{"xt":"urn:btih:d4efcf83d0ee44b7da9543abd7b90d4333281419","amp;dn":"Mutantes","amp;tr":["udp%3A%2F%2Ftracker.openbittorrent.com%3A80","udp%3A%2F%2Fopen.demonii.com%3A1337","udp%3A%2F%2Ftracker.coppersurfer.tk%3A6969","udp%3A%2F%2Fexodus.desync.com%3A6969"],"infoHash":"d4efcf83d0ee44b7da9543abd7b90d4333281419","infoHashBuffer":{"type":"Buffer","data":[212,239,207,131,208,238,68,183,218,149,67,171,215,185,13,67,51,40,20,25]},"announce":[],"urlList":[]}}