{"title":"MomsInControl: JoJo Kiss, Ryan Conner (Sharing The Shower 2) XXX","uid":15126462,"size":312553943,"categoryP":"porn","categoryS":"movie_clips","magnet":"?xt=urn:btih:e4febce64d761af605852d32c5ba430d912ad76a&amp;dn=MomsInControl%3A+JoJo+Kiss%2C+Ryan+Conner+%28Sharing+The+Shower+2%29+XXX&amp;tr=udp%3A%2F%2Ftracker.leechers-paradise.org%3A6969&amp;tr=udp%3A%2F%2Fzer0day.ch%3A1337&amp;tr=udp%3A%2F%2Fopen.demonii.com%3A1337&amp;tr=udp%3A%2F%2Ftracker.coppersurfer.tk%3A6969&amp;tr=udp%3A%2F%2Fexodus.desync.com%3A6969","seeders":8,"leechers":2,"uploader":"SudoSu","files":1,"time":1467115278,"description":"\nMore exclusive porn at:  https://thepiratebay.se/user/SudoSu/\r\n\r\n―――――――――――――――――――――――――\r\n ... : Screenshots : ... \r\n―――――――――――――――――――――――――   \nhttp://imgpremium.com/image/XRm \nhttp://imgpremium.com/image/XRI","torrent":{"xt":"urn:btih:e4febce64d761af605852d32c5ba430d912ad76a","amp;dn":"MomsInControl%3A+JoJo+Kiss%2C+Ryan+Conner+%28Sharing+The+Shower+2%29+XXX","amp;tr":["udp%3A%2F%2Ftracker.leechers-paradise.org%3A6969","udp%3A%2F%2Fzer0day.ch%3A1337","udp%3A%2F%2Fopen.demonii.com%3A1337","udp%3A%2F%2Ftracker.coppersurfer.tk%3A6969","udp%3A%2F%2Fexodus.desync.com%3A6969"],"infoHash":"e4febce64d761af605852d32c5ba430d912ad76a","infoHashBuffer":{"type":"Buffer","data":[228,254,188,230,77,118,26,246,5,133,45,50,197,186,67,13,145,42,215,106]},"announce":[],"urlList":[]}}