{"title":"Insidious 2010 720p BRRip x264-x0r","uid":11471333,"size":1905987458,"categoryP":"video","categoryS":"hd___movies","magnet":"?xt=urn:btih:f167265ef19bdd4fa02cf7e0a5e84fd47c23ba02&amp;dn=Insidious+2010+720p+BRRip+x264-x0r&amp;tr=udp%3A%2F%2Ftracker.openbittorrent.com%3A80&amp;tr=udp%3A%2F%2Fopen.demonii.com%3A1337&amp;tr=udp%3A%2F%2Ftracker.coppersurfer.tk%3A6969&amp;tr=udp%3A%2F%2Fexodus.desync.com%3A6969","seeders":9,"leechers":9,"uploader":"hotpena","files":5,"time":1416092917,"description":"\nCOVER: &lt;a href=&quot;\nhttp://www.imgili.com/viewer.php?file=61824156396848876555.jpg&quot; rel=&quot;nofollow&quot; target=&quot;_NEW&quot;&gt;\nhttp://www.imgili.com/viewer.php?file=61824156396848876555.jpg&lt;/a&gt;\n\nPLOT: \nA family looks to prevent evil spirits from trapping their comatose child in a realm called The Further.\n\nACTORS: \nPatrick Wilson, Rose Byrne, Ty Simpkins, Lin Shaye, Leigh Whannell, Angus Sampson, \n\nRELEASED: \n 1 April 2011 \n\nIMDB: &lt;a href=&quot;\nhttp://www.imdb.com/title/tt1591095/&quot; rel=&quot;nofollow&quot; target=&quot;_NEW&quot;&gt;\nhttp://www.imdb.com/title/tt1591095/&lt;/a&gt;\n\n\n\n Size: 1870598878 bytes (1.74 GiB), duration: 01:42:52, avg.bitrate: 2425 kb/s\nAudio: ac3, 48000 Hz, 5:1\nVideo: h264, yuv420p, 1280x532, 23.98 fps(r) (eng)\nSubtitles: eng \n\n\n\n\n Size: 35379407 bytes (33.74 MiB), duration: 00:01:50, avg.bitrate: 2573 kb/s\nAudio: aac, 48000 Hz, stereo (eng)\nVideo: h264, yuv420p, 848x360, 23.98 fps(r) (eng)\n &lt;a href=&quot;\nhttp://www.imgili.com/viewer.php?file=08994564171484777484.jpg&quot; rel=&quot;nofollow&quot; target=&quot;_NEW&quot;&gt;\nhttp://www.imgili.com/viewer.php?file=08994564171484777484.jpg&lt;/a&gt;\n &lt;a href=&quot;\nhttp://www.imgili.com/viewer.php?file=13695264607197560130.jpg&quot; rel=&quot;nofollow&quot; target=&quot;_NEW&quot;&gt;\nhttp://www.imgili.com/viewer.php?file=13695264607197560130.jpg&lt;/a&gt;\n  &lt;a href=&quot;\nhttp://www.imgili.com/viewer.php?file=14875987400519259919.jpg&quot; rel=&quot;nofollow&quot; target=&quot;_NEW&quot;&gt;\nhttp://www.imgili.com/viewer.php?file=14875987400519259919.jpg&lt;/a&gt;\n \n &lt;a href=&quot;\nhttp://www.imgili.com/viewer.php?file=70341980183318134334.jpg&quot; rel=&quot;nofollow&quot; target=&quot;_NEW&quot;&gt;\nhttp://www.imgili.com/viewer.php?file=70341980183318134334.jpg&lt;/a&gt;\n &lt;a href=&quot;\nhttp://www.imgili.com/viewer.php?file=55017009851558924685.jpg&quot; rel=&quot;nofollow&quot; target=&quot;_NEW&quot;&gt;\nhttp://www.imgili.com/viewer.php?file=55017009851558924685.jpg&lt;/a&gt;\n  &lt;a href=&quot;\nhttp://www.imgili.com/viewer.php?file=67414859362188880617.jpg&quot; rel=&quot;nofollow&quot; target=&quot;_NEW&quot;&gt;\nhttp://www.imgili.com/viewer.php?file=67414859362188880617.jpg&lt;/a&gt;\n \n\n\n\nDOWNLOAD AND ENJOY. \n\n KEEP IT FOR LONG SEEDING TO HELP OTHERS \n\n \n Thanks to : x0r\n Movie Share","torrent":{"xt":"urn:btih:f167265ef19bdd4fa02cf7e0a5e84fd47c23ba02","amp;dn":"Insidious+2010+720p+BRRip+x264-x0r","amp;tr":["udp%3A%2F%2Ftracker.openbittorrent.com%3A80","udp%3A%2F%2Fopen.demonii.com%3A1337","udp%3A%2F%2Ftracker.coppersurfer.tk%3A6969","udp%3A%2F%2Fexodus.desync.com%3A6969"],"infoHash":"f167265ef19bdd4fa02cf7e0a5e84fd47c23ba02","infoHashBuffer":{"type":"Buffer","data":[241,103,38,94,241,155,221,79,160,44,247,224,165,232,79,212,124,35,186,2]},"announce":[],"urlList":[]}}