{"title":"[MrAnal] - Jade Jantzen mp4 20 february 2015","uid":11714744,"size":380992756,"categoryP":"porn","categoryS":"other","magnet":"?xt=urn:btih:fda70179a0f83797ae90a41affcdc9c9a57d0d80&amp;dn=%5BMrAnal%5D+-+Jade+Jantzen+mp4+20+february+2015&amp;tr=udp%3A%2F%2Ftracker.openbittorrent.com%3A80&amp;tr=udp%3A%2F%2Fopen.demonii.com%3A1337&amp;tr=udp%3A%2F%2Ftracker.coppersurfer.tk%3A6969&amp;tr=udp%3A%2F%2Fexodus.desync.com%3A6969","seeders":9,"leechers":4,"uploader":"hrober","files":4,"time":1424515964,"description":"[MrAnal] - Jade Jantzen mp4 20 february 2015\n &lt;a href=&quot;\nhttp://xxxhost.info/img-54e8558479016.html&quot; rel=&quot;nofollow&quot; target=&quot;_NEW&quot;&gt;\nhttp://xxxhost.info/img-54e8558479016.html&lt;/a&gt;\n &lt;a href=&quot;\nhttp://xxxhost.info/img-54e8557bcd627.html&quot; rel=&quot;nofollow&quot; target=&quot;_NEW&quot;&gt;\nhttp://xxxhost.info/img-54e8557bcd627.html&lt;/a&gt;\n\n\n\nDon't forget to check all my Uploads :) &lt;a href=&quot;\nhttps://thepiratebay.se/user/hrober&quot; rel=&quot;nofollow&quot; target=&quot;_NEW&quot;&gt;\nhttps://thepiratebay.se/user/hrober&lt;/a&gt;","torrent":{"xt":"urn:btih:fda70179a0f83797ae90a41affcdc9c9a57d0d80","amp;dn":"%5BMrAnal%5D+-+Jade+Jantzen+mp4+20+february+2015","amp;tr":["udp%3A%2F%2Ftracker.openbittorrent.com%3A80","udp%3A%2F%2Fopen.demonii.com%3A1337","udp%3A%2F%2Ftracker.coppersurfer.tk%3A6969","udp%3A%2F%2Fexodus.desync.com%3A6969"],"infoHash":"fda70179a0f83797ae90a41affcdc9c9a57d0d80","infoHashBuffer":{"type":"Buffer","data":[253,167,1,121,160,248,55,151,174,144,164,26,255,205,201,201,165,125,13,128]},"announce":[],"urlList":[]}}