{"title":"VA - COOL JAZZ HOUSE The Best House Tunes with a Jazzy Feelings","uid":11889632,"size":293787277,"categoryP":"audio","categoryS":"music","magnet":"?xt=urn:btih:fe82fb4ad1368d7516b1e309a11927850f0658e1&amp;dn=VA+-+COOL+JAZZ+HOUSE+The+Best+House+Tunes+with+a+Jazzy+Feelings&amp;tr=udp%3A%2F%2Ftracker.openbittorrent.com%3A80&amp;tr=udp%3A%2F%2Fopen.demonii.com%3A1337&amp;tr=udp%3A%2F%2Ftracker.coppersurfer.tk%3A6969&amp;tr=udp%3A%2F%2Fexodus.desync.com%3A6969","seeders":9,"leechers":1,"uploader":"baby967","files":24,"time":1430942384,"description":" Artist(s) ..........:: Various Artist\n\n Title ..............:: COOL JAZZ HOUSE - The Best House Tunes With A Jazzy Feelings\n\n Record Label .......:: Irma Records Suonaphone\n\n Catalogue Number....:: IRM 1334\n\n Country.............:: EU\n\n Source .............:: WEB, CD Album, CDDA - Compilation, CD Rip\n\n Music Genre.........:: Electronic\n\n Music Style.........:: Deep House, Lounge, Downtempo, Soulful House, Left-Field House, Funky, Club House\n\n Quality ............:: CBR 320 kbps / 44.1kHz / Full Stereo / MS Stereo\n\n Format..............:: Mp3 / Separate Tracks (image+*m3u) / Lossy\n\n Encoder.............:: LAME v3.98r\n\n Tracks .............:: 20 Unmixed\n\n Total Time..........:: 02:02:13\n\n Total Size..........:: ~ 280 Mb\n\n Street Date.........:: 2015-April-28\n\n Rip Date............:: 2015-April-29\n\n\n\n                        Tracklist:\n                       -==========-\n\n\n 01. Amana Melome' - Caterpillar (Atjazz 7 Am Remix) 06:34\n\n 02. Duran, Garcia - Fus-Ion 04:39\n\n 03. Ltj Xperience - Feel The Real (Feat. Taka Boom) 07:05\n\n 04. Big Mojo - Please Have Mercy On Me (Groovy Deevibes Pacificalicius Remix) 08:13\n\n 05. Belladonna - I Wanna Boogie 07:59\n\n 06. Montego Bay - Same Old Sound (S-Tone Mix) 04:11\n\n 07. Jestofunk - For Your Precious Love 05:37\n\n 08. Double Dee - The More I Get More I Want (Vocal Mix) 05:39\n\n 09. Gazzara - Can't Hide Love (Montego Bay Club Mix) 04:58\n\n 10. Ltj Sound Machine - Mestizo 06:08\n\n 11. Dn3 - Channel 3 04:07\n\n 12. Pongo Groove - Amerika 06:04\n\n 13. Double Dee - Found Love (Soft House Remix) 05:23\n\n 14. The Black Mighty Orchestra - Groove To The Sky 04:41\n\n 15. Guido Nemola - Waiting 06:08\n\n 16. Clan Greco - Rotation (Eric Kupper Remix) 06:30\n\n 17. Santorini - A Ray Of Light (System Of Survival Remix) 08:50\n\n 18. Dipo - George Blooney (Luca Ferrari Deep Remix) 06:19\n\n 19. Blender - Trouble Jazz (Funky Mix) 05:12\n\n 20. Dj Umbi - Sonidos (Instrumental Mix) 07:46","torrent":{"xt":"urn:btih:fe82fb4ad1368d7516b1e309a11927850f0658e1","amp;dn":"VA+-+COOL+JAZZ+HOUSE+The+Best+House+Tunes+with+a+Jazzy+Feelings","amp;tr":["udp%3A%2F%2Ftracker.openbittorrent.com%3A80","udp%3A%2F%2Fopen.demonii.com%3A1337","udp%3A%2F%2Ftracker.coppersurfer.tk%3A6969","udp%3A%2F%2Fexodus.desync.com%3A6969"],"infoHash":"fe82fb4ad1368d7516b1e309a11927850f0658e1","infoHashBuffer":{"type":"Buffer","data":[254,130,251,74,209,54,141,117,22,177,227,9,161,25,39,133,15,6,88,225]},"announce":[],"urlList":[]}}